pyovpn_as/__init__.py
pyovpn_as/client.py
pyovpn_as/exceptions.py
pyovpn_as/groups.py
pyovpn_as/profile.py
pyovpn_as/server.py
pyovpn_as/users.py
pyovpn_as/utils.py
pyovpn_as/vpn.py
pyovpn_as/api/__init__.py
pyovpn_as/api/cli.py
pyovpn_as/api/exceptions.py
pyovpn_as/api/rpc.py
pyovpn_as/api/supported_methods.json
pyovpn_as-0.0.8.dist-info/LICENSE
pyovpn_as-0.0.8.dist-info/METADATA
pyovpn_as-0.0.8.dist-info/WHEEL
pyovpn_as-0.0.8.dist-info/top_level.txt
pyovpn_as-0.0.8.dist-info/RECORD
