Metadata-Version: 2.1
Name: pyovpn-as
Version: 0.0.8
Summary: A Python library built on XML-RPC that demystifies remote interaction with OpenVPN Access Server
Home-page: https://github.com/peritz/pyovpn-as
Download-URL: https://github.com/peritz/pyovpn-as/archive/v_0_0_8.tar.gz
Author: Peritz
Author-email: peritz@pardonmynoot.com
License: GPL
Keywords: OpenVPN,AccessServer,Access Server,XML-RPC
Classifier: Development Status :: 3 - Alpha
Classifier: Intended Audience :: Developers
Classifier: Topic :: Software Development :: Libraries
Classifier: License :: OSI Approved :: GNU General Public License v3 (GPLv3)
Classifier: Natural Language :: English
Classifier: Operating System :: OS Independent
Classifier: Programming Language :: Python :: 3
Classifier: Programming Language :: Python :: 3 :: Only
Classifier: Programming Language :: Python :: 3.6
Classifier: Programming Language :: Python :: 3.7
Classifier: Programming Language :: Python :: 3.8
Classifier: Programming Language :: Python :: 3.9
Classifier: Programming Language :: Python :: 3.10
License-File: LICENSE
